tableparse
