Metadata-Version: 2.1
Name: tableparse
Version: 0.7
Summary: A stand alone package for making string tables from 2D string arrays
Home-page: https://github.com/TommyGymer/Tableparse
Author: Tommy Gymer
Author-email: 84601129+TommyGymer@users.noreply.github.com
License: MIT
Keywords: TableParse
Platform: UNKNOWN
License-File: LICENSE
